MANIFEST.in
README.md
fastentrypoints.py
setup.py
bugone/__init__.py
bugone/bugnet.py
bugone/connector.py
bugone/dumper.py
bugone.egg-info/PKG-INFO
bugone.egg-info/SOURCES.txt
bugone.egg-info/dependency_links.txt
bugone.egg-info/entry_points.txt
bugone.egg-info/requires.txt
bugone.egg-info/top_level.txt