Metadata-Version: 1.1
Name: bugone
Version: 0.6
Summary: API to send/receive bugOne messages througt serial port or tcp mux
Home-page: https://github.com/jkx/bugone-python
Author: Jerome Kerdreux
Author-email: Jerome.Kerdreux@Finix.eu.org
License: GPL License
Keywords: RFM12,bugOne,Wireless,Home-Automation
Platform: any
Classifier: Programming Language :: Python
Classifier: Topic :: Software Development :: Libraries :: Python Modules
